setuptools_version_command.py
setuptools_version_command-99.9.dist-info/AUTHORS
setuptools_version_command-99.9.dist-info/LICENSE
setuptools_version_command-99.9.dist-info/METADATA
setuptools_version_command-99.9.dist-info/WHEEL
setuptools_version_command-99.9.dist-info/entry_points.txt
setuptools_version_command-99.9.dist-info/top_level.txt
setuptools_version_command-99.9.dist-info/version.txt
setuptools_version_command-99.9.dist-info/RECORD
