Metadata-Version: 2.1
Name: setuptools-version-command
Version: 99.9
Summary: Adds a command to dynamically get the version from the VCS of choice
Home-page: https://github.com/j0057/setuptools-version-command
Author: Joost Molenaar
Author-email: j.j.molenaar@gmail.com
License: http://opensource.org/licenses/MIT
Platform: UNKNOWN
Classifier: Framework :: Setuptools Plugin
Classifier: Intended Audience :: Developers
Classifier: License :: OSI Approved :: MIT License
Classifier: Programming Language :: Python
Classifier: Programming Language :: Python :: 2
Classifier: Programming Language :: Python :: 2.7
Classifier: Programming Language :: Python :: 3
Classifier: Programming Language :: Python :: 3.4
License-File: LICENSE
License-File: AUTHORS
Requires-Dist: setuptools
